buildbot_travis/VERSION
buildbot_travis/__init__.py
buildbot_travis/api.py
buildbot_travis/cmdline.py
buildbot_travis/configurator.py
buildbot_travis/important.py
buildbot_travis/mergereq.py
buildbot_travis/runner.py
buildbot_travis/travisyml.py
buildbot_travis/changes/__init__.py
buildbot_travis/changes/svnpoller.py
buildbot_travis/static/scripts.js
buildbot_travis/static/styles.css
buildbot_travis/static/tests.js
buildbot_travis/steps/__init__.py
buildbot_travis/steps/base.py
buildbot_travis/steps/create_steps.py
buildbot_travis/steps/spawner.py
buildbot_travis/tests/__init__.py
buildbot_travis/tests/test_configurator.py
buildbot_travis/tests/test_git.py
buildbot_travis/tests/test_important.py
buildbot_travis/tests/test_integration.py
buildbot_travis/tests/test_integration_buildbot.py
buildbot_travis/tests/test_plugins.py
buildbot_travis/tests/test_travisyml.py
buildbot_travis/ui/__init__.py
buildbot_travis/vcs/__init__.py
buildbot_travis/vcs/base.py
buildbot_travis/vcs/gerrit.py
buildbot_travis/vcs/git.py
buildbot_travis/vcs/github.py
buildbot_travis/vcs/svn.py
buildbot_travis-0.6.4.dist-info/LICENSE
buildbot_travis-0.6.4.dist-info/METADATA
buildbot_travis-0.6.4.dist-info/WHEEL
buildbot_travis-0.6.4.dist-info/entry_points.txt
buildbot_travis-0.6.4.dist-info/top_level.txt
buildbot_travis-0.6.4.dist-info/RECORD
