Metadata-Version: 2.1
Name: buildbot-travis
Version: 0.6.4
Summary: Travis CI implemented in Buildbot
Home-page: http://github.com/buildbot/buildbot_travis
Author: Buildbot community
Author-email: buildbot-devel@lists.sourceforge.net
License: MIT
Keywords: buildbot travis ci
Platform: UNKNOWN
Requires-Dist: setuptools
Requires-Dist: buildbot (>=0.9.6)
Requires-Dist: buildbot-www
Requires-Dist: buildbot-console-view
Requires-Dist: buildbot-waterfall-view
Requires-Dist: buildbot-worker
Requires-Dist: klein
Requires-Dist: urwid
Requires-Dist: PyYAML
Requires-Dist: txrequests
Requires-Dist: pyjade
Requires-Dist: txgithub
Requires-Dist: ldap3
Requires-Dist: hyper-sh
Requires-Dist: future
